README.rst
setup.py
DST/__init__.py
DST/datasets/CleanData.py
DST/datasets/DownloadData.py
DST/datasets/__init__.py
DST/domain_term/DomainTerm.py
DST/domain_term/__init__.py
DST/domain_thesaurus/DomainThesaurus.py
DST/domain_thesaurus/__init__.py
DST/phrase_detection/PhraseDetection.py
DST/phrase_detection/__init__.py
DST/semantic_related_word/SemanticRelatedWord.py
DST/semantic_related_word/__init__.py
DST/utils/DSUtil.py
DST/utils/TermUtil.py
DST/utils/VocabUtil.py
DST/utils/__init__.py
DST/word_discrimination/WordDiscrimination.py
DST/word_discrimination/__init__.py
DomainThesaurus.egg-info/PKG-INFO
DomainThesaurus.egg-info/SOURCES.txt
DomainThesaurus.egg-info/dependency_links.txt
DomainThesaurus.egg-info/requires.txt
DomainThesaurus.egg-info/top_level.txt