Metadata-Version: 1.2
Name: DomainThesaurus
Version: 1.1.5
Summary: extract domain thesaurus automatically
Home-page: https://github.com/DunZhang/DomainSpecificThesaurus
Author: ZhangDun, ChenXiang, Chunyang Chen
Author-email: dunnzhang0@gmail.com, xchencs@ntu.edu.cn, chunyang.chen@monash.edu
Maintainer: ZhangDun
Maintainer-email: dunnzhang0@gmail.com
License: MIT
Platform: UNKNOWN
Classifier: Development Status :: 2 - Pre-Alpha
Classifier: Operating System :: Microsoft :: Windows
Classifier: Operating System :: POSIX
Classifier: Operating System :: Unix
Classifier: Operating System :: MacOS
Classifier: Intended Audience :: Developers
Classifier: Intended Audience :: Science/Research
Classifier: Programming Language :: Python :: 3
Classifier: License :: OSI Approved :: MIT License
Classifier: Topic :: Scientific/Engineering :: Artificial Intelligence
